{"entries":{"420":{"id":"420","slayerPoints":{"value":0},"preferCap":{"value":1},"blockCap":{"value":1},"tasksCompleted":{"value":0},"taskStreak":{"value":0},"preferredTasks":[],"blockedTasks":[],"unlocksList":[],"slayerTask":{"assignment":31,"amount":{"value":14},"master":404},"slayerMaster":404,"graveDiggerProperties":{"points":{"value":2000},"attempts":{"value":3},"paidAttempts":{"value":0}},"openedGift":true,"unlcaimedPrizes":[]},"phantasye":{"id":"phantasye","slayerPoints":{"value":40500},"preferCap":{"value":1},"blockCap":{"value":1},"tasksCompleted":{"value":2},"taskStreak":{"value":0},"preferredTasks":[],"blockedTasks":[23],"unlocksList":[0,2,1],"slayerTask":{"assignment":38,"amount":{"value":12},"master":405},"slayerMaster":405,"herbSack":{},"paymentRunes":[565],"magicFindRating":{"value":130},"mythicalCapeCharges":{"value":0},"mythicalCapeTier":{"value":0},"graveDiggerProperties":{"points":{"value":530},"attempts":{"value":3},"paidAttempts":{"value":42}},"openedGift":true,"unlcaimedPrizes":[]},"michael":{"id":"michael","slayerPoints":{"value":0},"preferCap":{"value":1},"blockCap":{"value":1},"tasksCompleted":{"value":0},"taskStreak":{"value":0},"preferredTasks":[],"blockedTasks":[],"unlocksList":[],"slayerTask":{"assignment":19,"amount":{"value":154},"master":403},"slayerMaster":403,"graveDiggerProperties":{"points":{"value":563},"attempts":{"value":3},"paidAttempts":{"value":0}},"openedGift":true,"unlcaimedPrizes":[]},"Danny":{"id":"Danny","slayerPoints":{"value":303},"preferCap":{"value":1},"blockCap":{"value":1},"tasksCompleted":{"value":42},"taskStreak":{"value":21},"preferredTasks":[],"blockedTasks":[],"unlocksList":[0,2,3,5,4],"slayerTask":{"assignment":49,"amount":{"value":6},"master":405},"slayerMaster":405,"graveDiggerProperties":{"points":{"value":5},"attempts":{"value":3},"paidAttempts":{"value":0}},"openedGift":true,"unlcaimedPrizes":[]},"Irn Dru":{"id":"Irn Dru","slayerPoints":{"value":1},"preferCap":{"value":1},"blockCap":{"value":1},"tasksCompleted":{"value":1},"taskStreak":{"value":46},"preferredTasks":[],"blockedTasks":[],"unlocksList":[0,1,2,5],"slayerTask":{"assignment":6,"amount":{"value":91},"master":405},"slayerMaster":405,"graveDiggerProperties":{"points":{"value":0},"attempts":{"value":3},"paidAttempts":{"value":0}},"openedGift":false,"unlcaimedPrizes":[]},"crystall777":{"id":"crystall777","slayerPoints":{"value":96},"preferCap":{"value":1},"blockCap":{"value":1},"tasksCompleted":{"value":14},"taskStreak":{"value":9},"preferredTasks":[],"blockedTasks":[],"unlocksList":[],"slayerTask":{"assignment":20,"amount":{"value":131},"master":404},"slayerMaster":404,"herbSack":{},"paymentRunes":[],"graveDiggerProperties":{"points":{"value":1440},"attempts":{"value":3},"paidAttempts":{"value":0}},"openedGift":true,"unlcaimedPrizes":[]},"Savij":{"id":"Savij","slayerPoints":{"value":12},"preferCap":{"value":1},"blockCap":{"value":1},"tasksCompleted":{"value":1},"taskStreak":{"value":1},"preferredTasks":[],"blockedTasks":[],"unlocksList":[],"slayerTask":{"assignment":20,"amount":{"value":83},"master":6797},"slayerMaster":6797,"graveDiggerProperties":{"points":{"value":700},"attempts":{"value":3},"paidAttempts":{"value":0}},"openedGift":true,"unlcaimedPrizes":[]},"357mag":{"id":"357mag","slayerPoints":{"value":0},"preferCap":{"value":1},"blockCap":{"value":1},"tasksCompleted":{"value":0},"taskStreak":{"value":0},"preferredTasks":[],"blockedTasks":[],"unlocksList":[],"slayerTask":{"assignment":6,"amount":{"value":141},"master":404},"slayerMaster":404,"graveDiggerProperties":{"points":{"value":60},"attempts":{"value":3},"paidAttempts":{"value":0}},"openedGift":true,"unlcaimedPrizes":[]},"Jpd":{"id":"Jpd","slayerPoints":{"value":0},"preferCap":{"value":1},"blockCap":{"value":1},"tasksCompleted":{"value":0},"taskStreak":{"value":0},"preferredTasks":[],"blockedTasks":[],"unlocksList":[],"slayerTask":{"assignment":43,"amount":{"value":123},"master":404},"slayerMaster":404,"graveDiggerProperties":{"points":{"value":1590},"attempts":{"value":3},"paidAttempts":{"value":0}},"openedGift":true,"unlcaimedPrizes":[]},"Jon":{"id":"Jon","slayerPoints":{"value":23},"preferCap":{"value":1},"blockCap":{"value":1},"tasksCompleted":{"value":14},"taskStreak":{"value":14},"preferredTasks":[],"blockedTasks":[],"unlocksList":[0,3],"slayerTask":{"assignment":13,"amount":{"value":135},"master":405},"slayerMaster":405,"herbSack":{},"paymentRunes":[],"magicFindRating":{"value":0},"mythicalCapeCharges":{"value":0},"mythicalCapeTier":{"value":0},"graveDiggerProperties":{"points":{"value":790},"attempts":{"value":3},"paidAttempts":{"value":0}},"openedGift":true,"unlcaimedPrizes":[]},"erica":{"id":"erica","slayerPoints":{"value":768},"preferCap":{"value":1},"blockCap":{"value":1},"tasksCompleted":{"value":104},"taskStreak":{"value":36},"preferredTasks":[],"blockedTasks":[],"unlocksList":[0,2],"slayerTask":{"assignment":19,"amount":{"value":94},"master":405},"slayerMaster":405,"herbSack":{},"paymentRunes":[],"magicFindRating":{"value":0},"mythicalCapeCharges":{"value":0},"mythicalCapeTier":{"value":0},"graveDiggerProperties":{"points":{"value":1290},"attempts":{"value":3},"paidAttempts":{"value":0}},"openedGift":true,"unlcaimedPrizes":[]},"essex":{"id":"essex","slayerPoints":{"value":2},"preferCap":{"value":1},"blockCap":{"value":1},"tasksCompleted":{"value":2},"taskStreak":{"value":2},"preferredTasks":[],"blockedTasks":[],"unlocksList":[],"slayerTask":{"assignment":29,"amount":{"value":47},"master":402},"slayerMaster":402,"graveDiggerProperties":{"points":{"value":0},"attempts":{"value":3},"paidAttempts":{"value":0}},"openedGift":false,"unlcaimedPrizes":[]},"jaijairgh":{"id":"jaijairgh","slayerPoints":{"value":0},"preferCap":{"value":1},"blockCap":{"value":1},"tasksCompleted":{"value":0},"taskStreak":{"value":0},"preferredTasks":[],"blockedTasks":[],"unlocksList":[],"slayerTask":{"assignment":15,"amount":{"value":34},"master":401},"slayerMaster":401,"graveDiggerProperties":{"points":{"value":1390},"attempts":{"value":3},"paidAttempts":{"value":0}},"openedGift":true,"unlcaimedPrizes":[]},"super allie":{"id":"super allie","slayerPoints":{"value":317},"preferCap":{"value":1},"blockCap":{"value":1},"tasksCompleted":{"value":41},"taskStreak":{"value":38},"preferredTasks":[],"blockedTasks":[],"unlocksList":[0,2],"slayerMaster":404,"herbSack":{},"paymentRunes":[],"magicFindRating":{"value":0},"mythicalCapeCharges":{"value":0},"mythicalCapeTier":{"value":0},"graveDiggerProperties":{"points":{"value":1180},"attempts":{"value":3},"paidAttempts":{"value":0}},"openedGift":true,"unlcaimedPrizes":[]},"irn dru":{"id":"irn dru","slayerPoints":{"value":96},"preferCap":{"value":1},"blockCap":{"value":1},"tasksCompleted":{"value":78},"taskStreak":{"value":1},"preferredTasks":[7],"blockedTasks":[19],"unlocksList":[2,0,5,1],"slayerTask":{"assignment":9,"amount":{"value":106},"master":405},"slayerMaster":405,"herbSack":{},"paymentRunes":[],"graveDiggerProperties":{"points":{"value":1030},"attempts":{"value":3},"paidAttempts":{"value":0}},"openedGift":true,"unlcaimedPrizes":[]},"bacon":{"id":"bacon","slayerPoints":{"value":4},"preferCap":{"value":1},"blockCap":{"value":1},"tasksCompleted":{"value":1},"taskStreak":{"value":1},"preferredTasks":[],"blockedTasks":[],"unlocksList":[],"slayerMaster":403,"graveDiggerProperties":{"points":{"value":0},"attempts":{"value":3},"paidAttempts":{"value":0}},"openedGift":false,"unlcaimedPrizes":[]},"david":{"id":"david","slayerPoints":{"value":0},"preferCap":{"value":1},"blockCap":{"value":1},"tasksCompleted":{"value":0},"taskStreak":{"value":0},"preferredTasks":[],"blockedTasks":[],"unlocksList":[],"slayerTask":{"assignment":29,"amount":{"value":94},"master":403},"slayerMaster":403,"graveDiggerProperties":{"points":{"value":50},"attempts":{"value":3},"paidAttempts":{"value":0}},"openedGift":false,"unlcaimedPrizes":[]},"shorts":{"id":"shorts","slayerPoints":{"value":0},"preferCap":{"value":1},"blockCap":{"value":1},"tasksCompleted":{"value":0},"taskStreak":{"value":0},"preferredTasks":[],"blockedTasks":[],"unlocksList":[],"slayerTask":{"assignment":6,"amount":{"value":128},"master":404},"slayerMaster":404,"graveDiggerProperties":{"points":{"value":1890},"attempts":{"value":3},"paidAttempts":{"value":0}},"openedGift":true,"unlcaimedPrizes":[]},"TexasAg":{"id":"TexasAg","slayerPoints":{"value":0},"preferCap":{"value":1},"blockCap":{"value":1},"tasksCompleted":{"value":0},"taskStreak":{"value":0},"preferredTasks":[],"blockedTasks":[],"unlocksList":[],"slayerTask":{"assignment":23,"amount":{"value":84},"master":404},"slayerMaster":404,"graveDiggerProperties":{"points":{"value":0},"attempts":{"value":3},"paidAttempts":{"value":0}},"openedGift":false,"unlcaimedPrizes":[]},"droo":{"id":"droo","slayerPoints":{"value":4},"preferCap":{"value":1},"blockCap":{"value":1},"tasksCompleted":{"value":1},"taskStreak":{"value":1},"preferredTasks":[],"blockedTasks":[],"unlocksList":[],"slayerTask":{"assignment":31,"amount":{"value":29},"master":404},"slayerMaster":404,"herbSack":{},"paymentRunes":[],"graveDiggerProperties":{"points":{"value":1360},"attempts":{"value":3},"paidAttempts":{"value":0}},"openedGift":true,"unlcaimedPrizes":[]},"mr dreadlock":{"id":"mr dreadlock","slayerPoints":{"value":107},"preferCap":{"value":1},"blockCap":{"value":1},"tasksCompleted":{"value":27},"taskStreak":{"value":3},"preferredTasks":[],"blockedTasks":[],"unlocksList":[0,2],"slayerTask":{"assignment":53,"amount":{"value":21},"master":6797},"slayerMaster":6797,"graveDiggerProperties":{"points":{"value":160},"attempts":{"value":3},"paidAttempts":{"value":0}},"openedGift":true,"unlcaimedPrizes":[]},"exiled":{"id":"exiled","slayerPoints":{"value":9},"preferCap":{"value":1},"blockCap":{"value":1},"tasksCompleted":{"value":4},"taskStreak":{"value":4},"preferredTasks":[],"blockedTasks":[],"unlocksList":[],"slayerTask":{"assignment":30,"amount":{"value":53},"master":403},"slayerMaster":403,"graveDiggerProperties":{"points":{"value":30},"attempts":{"value":3},"paidAttempts":{"value":0}},"openedGift":true,"unlcaimedPrizes":[]},"Btw":{"id":"Btw","slayerPoints":{"value":15},"preferCap":{"value":1},"blockCap":{"value":1},"tasksCompleted":{"value":3},"taskStreak":{"value":3},"preferredTasks":[],"blockedTasks":[],"unlocksList":[],"slayerTask":{"assignment":42,"amount":{"value":92},"master":405},"slayerMaster":405,"herbSack":{},"paymentRunes":[],"graveDiggerProperties":{"points":{"value":230},"attempts":{"value":3},"paidAttempts":{"value":0}},"openedGift":true,"unlcaimedPrizes":[]},"metal allie":{"id":"metal allie","slayerPoints":{"value":3},"preferCap":{"value":1},"blockCap":{"value":1},"tasksCompleted":{"value":2},"taskStreak":{"value":2},"preferredTasks":[],"blockedTasks":[],"unlocksList":[],"slayerTask":{"assignment":19,"amount":{"value":14},"master":403},"slayerMaster":403,"graveDiggerProperties":{"points":{"value":0},"attempts":{"value":3},"paidAttempts":{"value":0}},"openedGift":false,"unlcaimedPrizes":[]},"all g lad":{"id":"all g lad","slayerPoints":{"value":1},"preferCap":{"value":1},"blockCap":{"value":1},"tasksCompleted":{"value":1},"taskStreak":{"value":1},"preferredTasks":[],"blockedTasks":[],"unlocksList":[],"slayerMaster":401,"graveDiggerProperties":{"points":{"value":500},"attempts":{"value":3},"paidAttempts":{"value":0}},"openedGift":true,"unlcaimedPrizes":[]},"ironman":{"id":"ironman","slayerPoints":{"value":53},"preferCap":{"value":1},"blockCap":{"value":1},"tasksCompleted":{"value":24},"taskStreak":{"value":14},"preferredTasks":[],"blockedTasks":[],"unlocksList":[0],"slayerMaster":405,"herbSack":{},"paymentRunes":[],"magicFindRating":{"value":0},"mythicalCapeCharges":{"value":0},"mythicalCapeTier":{"value":0},"graveDiggerProperties":{"points":{"value":0},"attempts":{"value":3},"paidAttempts":{"value":0}},"openedGift":false,"unlcaimedPrizes":[]},"milk man":{"id":"milk man","slayerPoints":{"value":0},"preferCap":{"value":1},"blockCap":{"value":1},"tasksCompleted":{"value":0},"taskStreak":{"value":0},"preferredTasks":[],"blockedTasks":[],"unlocksList":[],"slayerTask":{"assignment":23,"amount":{"value":117},"master":404},"slayerMaster":405,"graveDiggerProperties":{"points":{"value":0},"attempts":{"value":3},"paidAttempts":{"value":0}},"openedGift":false,"unlcaimedPrizes":[]},"s t o r y":{"id":"s t o r y","slayerPoints":{"value":0},"preferCap":{"value":1},"blockCap":{"value":1},"tasksCompleted":{"value":0},"taskStreak":{"value":0},"preferredTasks":[],"blockedTasks":[],"unlocksList":[],"slayerTask":{"assignment":31,"amount":{"value":26},"master":405},"slayerMaster":404,"graveDiggerProperties":{"points":{"value":700},"attempts":{"value":3},"paidAttempts":{"value":0}},"openedGift":false,"unlcaimedPrizes":[]},"oracle":{"id":"oracle","slayerPoints":{"value":0},"preferCap":{"value":1},"blockCap":{"value":1},"tasksCompleted":{"value":0},"taskStreak":{"value":0},"preferredTasks":[],"blockedTasks":[],"unlocksList":[],"slayerTask":{"assignment":17,"amount":{"value":18},"master":405},"slayerMaster":405,"graveDiggerProperties":{"points":{"value":60},"attempts":{"value":3},"paidAttempts":{"value":0}},"openedGift":false,"unlcaimedPrizes":[]},"HunterRayne":{"id":"HunterRayne","slayerPoints":{"value":10},"preferCap":{"value":1},"blockCap":{"value":1},"tasksCompleted":{"value":6},"taskStreak":{"value":6},"preferredTasks":[],"blockedTasks":[],"unlocksList":[],"slayerMaster":401,"graveDiggerProperties":{"points":{"value":0},"attempts":{"value":3},"paidAttempts":{"value":0}},"openedGift":false,"unlcaimedPrizes":[]},"iron dreads":{"id":"iron dreads","slayerPoints":{"value":1},"preferCap":{"value":1},"blockCap":{"value":1},"tasksCompleted":{"value":1},"taskStreak":{"value":1},"preferredTasks":[],"blockedTasks":[],"unlocksList":[],"slayerTask":{"assignment":37,"amount":{"value":61},"master":402},"slayerMaster":402,"graveDiggerProperties":{"points":{"value":0},"attempts":{"value":3},"paidAttempts":{"value":0}},"openedGift":false,"unlcaimedPrizes":[]},"og crystal":{"id":"og crystal","slayerPoints":{"value":157},"preferCap":{"value":1},"blockCap":{"value":1},"tasksCompleted":{"value":35},"taskStreak":{"value":35},"preferredTasks":[],"blockedTasks":[],"unlocksList":[0],"slayerTask":{"assignment":25,"amount":{"value":128},"master":404},"slayerMaster":404,"herbSack":{},"paymentRunes":[],"magicFindRating":{"value":0},"mythicalCapeCharges":{"value":0},"mythicalCapeTier":{"value":0},"graveDiggerProperties":{"points":{"value":30},"attempts":{"value":3},"paidAttempts":{"value":0}},"openedGift":false,"unlcaimedPrizes":[]},"ilone":{"id":"ilone","slayerPoints":{"value":1},"preferCap":{"value":1},"blockCap":{"value":1},"tasksCompleted":{"value":1},"taskStreak":{"value":1},"preferredTasks":[],"blockedTasks":[],"unlocksList":[],"slayerTask":{"assignment":40,"amount":{"value":38},"master":401},"slayerMaster":401,"graveDiggerProperties":{"points":{"value":0},"attempts":{"value":3},"paidAttempts":{"value":0}},"openedGift":false,"unlcaimedPrizes":[]},"nameside":{"id":"nameside","slayerPoints":{"value":7},"preferCap":{"value":1},"blockCap":{"value":1},"tasksCompleted":{"value":4},"taskStreak":{"value":4},"preferredTasks":[],"blockedTasks":[],"unlocksList":[],"slayerTask":{"assignment":8,"amount":{"value":31},"master":403},"slayerMaster":403,"graveDiggerProperties":{"points":{"value":0},"attempts":{"value":3},"paidAttempts":{"value":0}},"openedGift":false,"unlcaimedPrizes":[]},"Haki":{"id":"Haki","slayerPoints":{"value":0},"preferCap":{"value":1},"blockCap":{"value":1},"tasksCompleted":{"value":2},"taskStreak":{"value":2},"preferredTasks":[],"blockedTasks":[],"unlocksList":[],"slayerTask":{"assignment":0,"amount":{"value":81},"master":403},"slayerMaster":403,"graveDiggerProperties":{"points":{"value":0},"attempts":{"value":3},"paidAttempts":{"value":0}},"openedGift":false,"unlcaimedPrizes":[]},"haki":{"id":"haki","slayerPoints":{"value":0},"preferCap":{"value":1},"blockCap":{"value":1},"tasksCompleted":{"value":0},"taskStreak":{"value":0},"preferredTasks":[],"blockedTasks":[],"unlocksList":[],"slayerTask":{"assignment":35,"amount":{"value":82},"master":403},"slayerMaster":403,"graveDiggerProperties":{"points":{"value":0},"attempts":{"value":3},"paidAttempts":{"value":0}},"openedGift":false,"unlcaimedPrizes":[]},"Robert":{"id":"Robert","slayerPoints":{"value":0},"preferCap":{"value":1},"blockCap":{"value":1},"tasksCompleted":{"value":0},"taskStreak":{"value":0},"preferredTasks":[],"blockedTasks":[],"unlocksList":[],"slayerTask":{"assignment":31,"amount":{"value":29},"master":404},"slayerMaster":404,"graveDiggerProperties":{"points":{"value":0},"attempts":{"value":3},"paidAttempts":{"value":0}},"openedGift":false,"unlcaimedPrizes":[]},"Og crystal":{"id":"Og crystal","slayerPoints":{"value":0},"preferCap":{"value":1},"blockCap":{"value":1},"tasksCompleted":{"value":0},"taskStreak":{"value":0},"preferredTasks":[],"blockedTasks":[],"unlocksList":[],"slayerTask":{"assignment":12,"amount":{"value":101},"master":404},"slayerMaster":404,"graveDiggerProperties":{"points":{"value":0},"attempts":{"value":3},"paidAttempts":{"value":0}},"openedGift":false,"unlcaimedPrizes":[]},"r e v":{"id":"r e v","slayerPoints":{"value":9},"preferCap":{"value":1},"blockCap":{"value":1},"tasksCompleted":{"value":3},"taskStreak":{"value":3},"preferredTasks":[],"blockedTasks":[],"unlocksList":[],"slayerMaster":404,"graveDiggerProperties":{"points":{"value":0},"attempts":{"value":3},"paidAttempts":{"value":0}},"openedGift":false,"unlcaimedPrizes":[]},"castle wars":{"id":"castle wars","slayerPoints":{"value":1},"preferCap":{"value":1},"blockCap":{"value":1},"tasksCompleted":{"value":1},"taskStreak":{"value":1},"preferredTasks":[],"blockedTasks":[],"unlocksList":[],"slayerTask":{"assignment":21,"amount":{"value":27},"master":402},"slayerMaster":402,"graveDiggerProperties":{"points":{"value":0},"attempts":{"value":3},"paidAttempts":{"value":0}},"openedGift":false,"unlcaimedPrizes":[]},"teh prayer":{"id":"teh prayer","slayerPoints":{"value":0},"preferCap":{"value":1},"blockCap":{"value":1},"tasksCompleted":{"value":0},"taskStreak":{"value":0},"preferredTasks":[],"blockedTasks":[],"unlocksList":[],"slayerTask":{"assignment":44,"amount":{"value":18},"master":401},"slayerMaster":401,"graveDiggerProperties":{"points":{"value":0},"attempts":{"value":3},"paidAttempts":{"value":0}},"openedGift":false,"unlcaimedPrizes":[]},"mimic":{"id":"mimic","slayerPoints":{"value":1},"preferCap":{"value":1},"blockCap":{"value":1},"tasksCompleted":{"value":1},"taskStreak":{"value":1},"preferredTasks":[],"blockedTasks":[],"unlocksList":[],"slayerMaster":401,"graveDiggerProperties":{"points":{"value":0},"attempts":{"value":3},"paidAttempts":{"value":0}},"openedGift":false,"unlcaimedPrizes":[]},"azia":{"id":"azia","slayerPoints":{"value":0},"preferCap":{"value":1},"blockCap":{"value":1},"tasksCompleted":{"value":0},"taskStreak":{"value":0},"preferredTasks":[],"blockedTasks":[],"unlocksList":[],"slayerTask":{"assignment":44,"amount":{"value":48},"master":401},"slayerMaster":401,"graveDiggerProperties":{"points":{"value":0},"attempts":{"value":3},"paidAttempts":{"value":0}},"openedGift":false,"unlcaimedPrizes":[]},"Canada":{"id":"Canada","slayerPoints":{"value":9},"preferCap":{"value":1},"blockCap":{"value":1},"tasksCompleted":{"value":4},"taskStreak":{"value":4},"preferredTasks":[],"blockedTasks":[],"unlocksList":[],"slayerTask":{"assignment":12,"amount":{"value":79},"master":404},"slayerMaster":404,"graveDiggerProperties":{"points":{"value":0},"attempts":{"value":3},"paidAttempts":{"value":0}},"openedGift":false,"unlcaimedPrizes":[]},"zhockace":{"id":"zhockace","slayerPoints":{"value":51},"preferCap":{"value":1},"blockCap":{"value":1},"tasksCompleted":{"value":10},"taskStreak":{"value":1},"preferredTasks":[],"blockedTasks":[],"unlocksList":[],"slayerTask":{"assignment":43,"amount":{"value":165},"master":6797},"slayerMaster":6797,"graveDiggerProperties":{"points":{"value":0},"attempts":{"value":3},"paidAttempts":{"value":0}},"openedGift":false,"unlcaimedPrizes":[]},"Michael":{"id":"Michael","slayerPoints":{"value":3},"preferCap":{"value":1},"blockCap":{"value":1},"tasksCompleted":{"value":2},"taskStreak":{"value":2},"preferredTasks":[],"blockedTasks":[],"unlocksList":[],"slayerMaster":402,"graveDiggerProperties":{"points":{"value":0},"attempts":{"value":3},"paidAttempts":{"value":0}},"openedGift":false,"unlcaimedPrizes":[]},"bad badger":{"id":"bad badger","slayerPoints":{"value":15},"preferCap":{"value":1},"blockCap":{"value":1},"tasksCompleted":{"value":5},"taskStreak":{"value":5},"preferredTasks":[],"blockedTasks":[],"unlocksList":[],"slayerTask":{"assignment":8,"amount":{"value":77},"master":403},"slayerMaster":403,"graveDiggerProperties":{"points":{"value":0},"attempts":{"value":3},"paidAttempts":{"value":0}},"openedGift":false,"unlcaimedPrizes":[]},"myllow":{"id":"myllow","slayerPoints":{"value":0},"preferCap":{"value":1},"blockCap":{"value":1},"tasksCompleted":{"value":0},"taskStreak":{"value":0},"preferredTasks":[],"blockedTasks":[],"unlocksList":[],"slayerTask":{"assignment":44,"amount":{"value":27},"master":401},"slayerMaster":401,"graveDiggerProperties":{"points":{"value":0},"attempts":{"value":3},"paidAttempts":{"value":0}},"openedGift":false,"unlcaimedPrizes":[]},"Shake":{"id":"Shake","slayerPoints":{"value":7},"preferCap":{"value":1},"blockCap":{"value":1},"tasksCompleted":{"value":3},"taskStreak":{"value":3},"preferredTasks":[],"blockedTasks":[],"unlocksList":[],"slayerMaster":403,"graveDiggerProperties":{"points":{"value":0},"attempts":{"value":3},"paidAttempts":{"value":0}},"openedGift":false,"unlcaimedPrizes":[]},"DBM":{"id":"DBM","slayerPoints":{"value":0},"preferCap":{"value":1},"blockCap":{"value":1},"tasksCompleted":{"value":0},"taskStreak":{"value":0},"preferredTasks":[],"blockedTasks":[],"unlocksList":[],"slayerTask":{"assignment":40,"amount":{"value":22},"master":401},"slayerMaster":401,"graveDiggerProperties":{"points":{"value":0},"attempts":{"value":3},"paidAttempts":{"value":0}},"openedGift":false,"unlcaimedPrizes":[]},"officialmm":{"id":"officialmm","slayerPoints":{"value":30},"preferCap":{"value":1},"blockCap":{"value":1},"tasksCompleted":{"value":3},"taskStreak":{"value":3},"preferredTasks":[],"blockedTasks":[],"unlocksList":[],"slayerTask":{"assignment":34,"amount":{"value":44},"master":404},"slayerMaster":404,"herbSack":{},"paymentRunes":[],"magicFindRating":{"value":0},"mythicalCapeCharges":{"value":0},"mythicalCapeTier":{"value":0},"graveDiggerProperties":{"points":{"value":0},"attempts":{"value":3},"paidAttempts":{"value":0}},"openedGift":false,"unlcaimedPrizes":[]},"Jroc":{"id":"Jroc","slayerPoints":{"value":13},"preferCap":{"value":1},"blockCap":{"value":1},"tasksCompleted":{"value":4},"taskStreak":{"value":4},"preferredTasks":[],"blockedTasks":[],"unlocksList":[],"slayerTask":{"assignment":19,"amount":{"value":73},"master":404},"slayerMaster":404,"graveDiggerProperties":{"points":{"value":0},"attempts":{"value":3},"paidAttempts":{"value":0}},"openedGift":false,"unlcaimedPrizes":[]},"Tomass":{"id":"Tomass","slayerPoints":{"value":343},"preferCap":{"value":1},"blockCap":{"value":1},"tasksCompleted":{"value":26},"taskStreak":{"value":26},"preferredTasks":[],"blockedTasks":[],"unlocksList":[],"slayerTask":{"assignment":23,"amount":{"value":142},"master":6797},"slayerMaster":6797,"herbSack":{},"paymentRunes":[],"magicFindRating":{"value":0},"mythicalCapeCharges":{"value":0},"mythicalCapeTier":{"value":0},"graveDiggerProperties":{"points":{"value":0},"attempts":{"value":3},"paidAttempts":{"value":0}},"openedGift":false,"unlcaimedPrizes":[]},"daddy":{"id":"daddy","slayerPoints":{"value":1},"preferCap":{"value":1},"blockCap":{"value":1},"tasksCompleted":{"value":1},"taskStreak":{"value":1},"preferredTasks":[],"blockedTasks":[],"unlocksList":[],"slayerMaster":401,"graveDiggerProperties":{"points":{"value":0},"attempts":{"value":3},"paidAttempts":{"value":0}},"openedGift":false,"unlcaimedPrizes":[]},"Dexx":{"id":"Dexx","slayerPoints":{"value":189},"preferCap":{"value":1},"blockCap":{"value":1},"tasksCompleted":{"value":16},"taskStreak":{"value":16},"preferredTasks":[],"blockedTasks":[],"unlocksList":[],"slayerMaster":6797,"herbSack":{},"paymentRunes":[],"magicFindRating":{"value":0},"mythicalCapeCharges":{"value":0},"mythicalCapeTier":{"value":0},"graveDiggerProperties":{"points":{"value":0},"attempts":{"value":3},"paidAttempts":{"value":0}},"openedGift":false,"unlcaimedPrizes":[]},"Yosh":{"id":"Yosh","slayerPoints":{"value":1},"preferCap":{"value":1},"blockCap":{"value":1},"tasksCompleted":{"value":1},"taskStreak":{"value":0},"preferredTasks":[],"blockedTasks":[],"unlocksList":[],"slayerTask":{"assignment":19,"amount":{"value":99},"master":403},"slayerMaster":403,"herbSack":{},"paymentRunes":[],"graveDiggerProperties":{"points":{"value":0},"attempts":{"value":3},"paidAttempts":{"value":0}},"openedGift":false,"unlcaimedPrizes":[]},"Christian":{"id":"Christian","slayerPoints":{"value":104},"preferCap":{"value":1},"blockCap":{"value":1},"tasksCompleted":{"value":14},"taskStreak":{"value":1},"preferredTasks":[],"blockedTasks":[],"unlocksList":[],"slayerMaster":6797,"herbSack":{},"paymentRunes":[],"magicFindRating":{"value":400},"mythicalCapeCharges":{"value":0},"mythicalCapeTier":{"value":0},"graveDiggerProperties":{"points":{"value":0},"attempts":{"value":3},"paidAttempts":{"value":0}},"openedGift":false,"unlcaimedPrizes":[]},"Disorderly":{"id":"Disorderly","slayerPoints":{"value":154},"preferCap":{"value":1},"blockCap":{"value":1},"tasksCompleted":{"value":15},"taskStreak":{"value":1},"preferredTasks":[],"blockedTasks":[],"unlocksList":[],"slayerTask":{"assignment":7,"amount":{"value":13},"master":405},"slayerMaster":405,"herbSack":{},"paymentRunes":[],"graveDiggerProperties":{"points":{"value":0},"attempts":{"value":3},"paidAttempts":{"value":0}},"openedGift":false,"unlcaimedPrizes":[]},"youdiesocry":{"id":"youdiesocry","slayerPoints":{"value":13},"preferCap":{"value":1},"blockCap":{"value":1},"tasksCompleted":{"value":5},"taskStreak":{"value":5},"preferredTasks":[],"blockedTasks":[],"unlocksList":[],"slayerTask":{"assignment":3,"amount":{"value":99},"master":403},"slayerMaster":403,"graveDiggerProperties":{"points":{"value":0},"attempts":{"value":3},"paidAttempts":{"value":0}},"openedGift":false,"unlcaimedPrizes":[]},"xero":{"id":"xero","slayerPoints":{"value":0},"preferCap":{"value":1},"blockCap":{"value":1},"tasksCompleted":{"value":0},"taskStreak":{"value":0},"preferredTasks":[],"blockedTasks":[],"unlocksList":[],"slayerTask":{"assignment":22,"amount":{"value":23},"master":401},"slayerMaster":401,"graveDiggerProperties":{"points":{"value":0},"attempts":{"value":3},"paidAttempts":{"value":0}},"openedGift":false,"unlcaimedPrizes":[]},"pepperoni":{"id":"pepperoni","slayerPoints":{"value":1},"preferCap":{"value":1},"blockCap":{"value":1},"tasksCompleted":{"value":1},"taskStreak":{"value":1},"preferredTasks":[],"blockedTasks":[],"unlocksList":[],"slayerMaster":401,"herbSack":{},"paymentRunes":[],"graveDiggerProperties":{"points":{"value":0},"attempts":{"value":3},"paidAttempts":{"value":0}},"openedGift":false,"unlcaimedPrizes":[]},"brazen":{"id":"brazen","slayerPoints":{"value":173},"preferCap":{"value":1},"blockCap":{"value":1},"tasksCompleted":{"value":218},"taskStreak":{"value":172},"preferredTasks":[],"blockedTasks":[],"unlocksList":[],"slayerTask":{"assignment":19,"amount":{"value":70},"master":404},"slayerMaster":404,"herbSack":{},"paymentRunes":[556,558,555,557,554,559,564,562,9075,560,561,566],"magicFindRating":{"value":0},"mythicalCapeCharges":{"value":0},"mythicalCapeTier":{"value":0},"graveDiggerProperties":{"points":{"value":0},"attempts":{"value":3},"paidAttempts":{"value":0}},"openedGift":false,"unlcaimedPrizes":[]},"fosh":{"id":"fosh","slayerPoints":{"value":187},"preferCap":{"value":1},"blockCap":{"value":1},"tasksCompleted":{"value":18},"taskStreak":{"value":11},"preferredTasks":[],"blockedTasks":[],"unlocksList":[],"slayerTask":{"assignment":19,"amount":{"value":92},"master":6797},"slayerMaster":6797,"herbSack":{},"paymentRunes":[],"magicFindRating":{"value":0},"mythicalCapeCharges":{"value":0},"mythicalCapeTier":{"value":0},"graveDiggerProperties":{"points":{"value":0},"attempts":{"value":3},"paidAttempts":{"value":0}},"openedGift":false,"unlcaimedPrizes":[]},"zixxen":{"id":"zixxen","slayerPoints":{"value":19},"preferCap":{"value":1},"blockCap":{"value":1},"tasksCompleted":{"value":6},"taskStreak":{"value":6},"preferredTasks":[],"blockedTasks":[],"unlocksList":[],"slayerMaster":403,"herbSack":{},"paymentRunes":[],"graveDiggerProperties":{"points":{"value":0},"attempts":{"value":3},"paidAttempts":{"value":0}},"openedGift":false,"unlcaimedPrizes":[]},"the":{"id":"the","slayerPoints":{"value":173},"preferCap":{"value":1},"blockCap":{"value":1},"tasksCompleted":{"value":16},"taskStreak":{"value":11},"preferredTasks":[],"blockedTasks":[],"unlocksList":[],"slayerMaster":404,"herbSack":{},"paymentRunes":[],"graveDiggerProperties":{"points":{"value":0},"attempts":{"value":3},"paidAttempts":{"value":0}},"openedGift":false,"unlcaimedPrizes":[]},"foshv2":{"id":"foshv2","slayerPoints":{"value":2},"preferCap":{"value":1},"blockCap":{"value":1},"tasksCompleted":{"value":2},"taskStreak":{"value":2},"preferredTasks":[],"blockedTasks":[],"unlocksList":[],"slayerTask":{"assignment":5,"amount":{"value":43},"master":401},"slayerMaster":401,"herbSack":{},"paymentRunes":[],"magicFindRating":{"value":0},"mythicalCapeCharges":{"value":0},"mythicalCapeTier":{"value":0},"graveDiggerProperties":{"points":{"value":0},"attempts":{"value":3},"paidAttempts":{"value":0}},"openedGift":false,"unlcaimedPrizes":[]},"zixx":{"id":"zixx","slayerPoints":{"value":0},"preferCap":{"value":1},"blockCap":{"value":1},"tasksCompleted":{"value":0},"taskStreak":{"value":0},"preferredTasks":[],"blockedTasks":[],"unlocksList":[],"slayerTask":{"assignment":40,"amount":{"value":33},"master":401},"slayerMaster":401,"herbSack":{},"paymentRunes":[],"graveDiggerProperties":{"points":{"value":0},"attempts":{"value":3},"paidAttempts":{"value":0}},"openedGift":false,"unlcaimedPrizes":[]},"dwift":{"id":"dwift","slayerPoints":{"value":1},"preferCap":{"value":1},"blockCap":{"value":1},"tasksCompleted":{"value":1},"taskStreak":{"value":1},"preferredTasks":[],"blockedTasks":[],"unlocksList":[],"slayerTask":{"assignment":14,"amount":{"value":29},"master":403},"slayerMaster":403,"herbSack":{},"paymentRunes":[],"graveDiggerProperties":{"points":{"value":0},"attempts":{"value":3},"paidAttempts":{"value":0}},"openedGift":false,"unlcaimedPrizes":[]},"beat rice":{"id":"beat rice","slayerPoints":{"value":3},"preferCap":{"value":1},"blockCap":{"value":1},"tasksCompleted":{"value":2},"taskStreak":{"value":2},"preferredTasks":[],"blockedTasks":[],"unlocksList":[],"slayerTask":{"assignment":2,"amount":{"value":48},"master":403},"slayerMaster":403,"herbSack":{},"paymentRunes":[],"graveDiggerProperties":{"points":{"value":0},"attempts":{"value":3},"paidAttempts":{"value":0}},"openedGift":false,"unlcaimedPrizes":[]},"king cum":{"id":"king cum","slayerPoints":{"value":15},"preferCap":{"value":1},"blockCap":{"value":1},"tasksCompleted":{"value":5},"taskStreak":{"value":5},"preferredTasks":[],"blockedTasks":[],"unlocksList":[],"slayerTask":{"assignment":31,"amount":{"value":31},"master":404},"slayerMaster":404,"herbSack":{},"paymentRunes":[],"magicFindRating":{"value":0},"mythicalCapeCharges":{"value":0},"mythicalCapeTier":{"value":0},"graveDiggerProperties":{"points":{"value":0},"attempts":{"value":3},"paidAttempts":{"value":0}},"openedGift":false,"unlcaimedPrizes":[]},"nick":{"id":"nick","slayerPoints":{"value":5},"preferCap":{"value":1},"blockCap":{"value":1},"tasksCompleted":{"value":3},"taskStreak":{"value":3},"preferredTasks":[],"blockedTasks":[],"unlocksList":[],"slayerTask":{"assignment":12,"amount":{"value":39},"master":403},"slayerMaster":403,"herbSack":{},"paymentRunes":[],"magicFindRating":{"value":0},"mythicalCapeCharges":{"value":0},"mythicalCapeTier":{"value":0},"graveDiggerProperties":{"points":{"value":0},"attempts":{"value":3},"paidAttempts":{"value":0}},"openedGift":false,"unlcaimedPrizes":[]},"17":{"id":"17","slayerPoints":{"value":1},"preferCap":{"value":1},"blockCap":{"value":1},"tasksCompleted":{"value":1},"taskStreak":{"value":1},"preferredTasks":[],"blockedTasks":[],"unlocksList":[],"slayerTask":{"assignment":44,"amount":{"value":48},"master":401},"slayerMaster":401,"herbSack":{},"paymentRunes":[],"magicFindRating":{"value":0},"mythicalCapeCharges":{"value":0},"mythicalCapeTier":{"value":0},"graveDiggerProperties":{"points":{"value":0},"attempts":{"value":3},"paidAttempts":{"value":0}},"openedGift":false,"unlcaimedPrizes":[]},"u mad bro":{"id":"u mad bro","slayerPoints":{"value":0},"preferCap":{"value":1},"blockCap":{"value":1},"tasksCompleted":{"value":0},"taskStreak":{"value":0},"preferredTasks":[],"blockedTasks":[],"unlocksList":[],"slayerTask":{"assignment":22,"amount":{"value":34},"master":401},"slayerMaster":401,"herbSack":{},"paymentRunes":[],"magicFindRating":{"value":0},"mythicalCapeCharges":{"value":0},"mythicalCapeTier":{"value":0},"graveDiggerProperties":{"points":{"value":0},"attempts":{"value":3},"paidAttempts":{"value":0}},"openedGift":false,"unlcaimedPrizes":[]},"blazen":{"id":"blazen","slayerPoints":{"value":111},"preferCap":{"value":1},"blockCap":{"value":1},"tasksCompleted":{"value":79},"taskStreak":{"value":79},"preferredTasks":[],"blockedTasks":[],"unlocksList":[],"slayerMaster":401,"herbSack":{},"paymentRunes":[],"magicFindRating":{"value":0},"mythicalCapeCharges":{"value":0},"mythicalCapeTier":{"value":0},"graveDiggerProperties":{"points":{"value":0},"attempts":{"value":3},"paidAttempts":{"value":0}},"openedGift":false,"unlcaimedPrizes":[]},"nacho":{"id":"nacho","slayerPoints":{"value":9},"preferCap":{"value":1},"blockCap":{"value":1},"tasksCompleted":{"value":4},"taskStreak":{"value":4},"preferredTasks":[],"blockedTasks":[],"unlocksList":[],"slayerMaster":403,"herbSack":{},"paymentRunes":[],"magicFindRating":{"value":0},"mythicalCapeCharges":{"value":0},"mythicalCapeTier":{"value":0},"graveDiggerProperties":{"points":{"value":0},"attempts":{"value":3},"paidAttempts":{"value":0}},"openedGift":false,"unlcaimedPrizes":[]},"tusenlappen":{"id":"tusenlappen","slayerPoints":{"value":1},"preferCap":{"value":1},"blockCap":{"value":1},"tasksCompleted":{"value":1},"taskStreak":{"value":1},"preferredTasks":[],"blockedTasks":[],"unlocksList":[],"slayerTask":{"assignment":39,"amount":{"value":46},"master":402},"slayerMaster":402,"herbSack":{},"paymentRunes":[],"magicFindRating":{"value":0},"mythicalCapeCharges":{"value":0},"mythicalCapeTier":{"value":0},"graveDiggerProperties":{"points":{"value":0},"attempts":{"value":3},"paidAttempts":{"value":0}},"openedGift":false,"unlcaimedPrizes":[]},"nulls":{"id":"nulls","slayerPoints":{"value":26},"preferCap":{"value":1},"blockCap":{"value":1},"tasksCompleted":{"value":9},"taskStreak":{"value":0},"preferredTasks":[],"blockedTasks":[],"unlocksList":[],"slayerTask":{"assignment":19,"amount":{"value":97},"master":404},"slayerMaster":404,"herbSack":{},"paymentRunes":[],"magicFindRating":{"value":0},"mythicalCapeCharges":{"value":0},"mythicalCapeTier":{"value":0},"graveDiggerProperties":{"points":{"value":0},"attempts":{"value":3},"paidAttempts":{"value":0}},"openedGift":false,"unlcaimedPrizes":[]},"kaylee":{"id":"kaylee","slayerPoints":{"value":7},"preferCap":{"value":1},"blockCap":{"value":1},"tasksCompleted":{"value":3},"taskStreak":{"value":1},"preferredTasks":[],"blockedTasks":[],"unlocksList":[],"slayerTask":{"assignment":8,"amount":{"value":62},"master":403},"slayerMaster":403,"herbSack":{},"paymentRunes":[],"magicFindRating":{"value":0},"mythicalCapeCharges":{"value":0},"mythicalCapeTier":{"value":0},"graveDiggerProperties":{"points":{"value":0},"attempts":{"value":3},"paidAttempts":{"value":0}},"openedGift":false,"unlcaimedPrizes":[]},"archezra":{"id":"archezra","slayerPoints":{"value":3},"preferCap":{"value":1},"blockCap":{"value":1},"tasksCompleted":{"value":3},"taskStreak":{"value":3},"preferredTasks":[],"blockedTasks":[],"unlocksList":[],"slayerTask":{"assignment":5,"amount":{"value":47},"master":401},"slayerMaster":401,"herbSack":{},"paymentRunes":[],"magicFindRating":{"value":0},"mythicalCapeCharges":{"value":0},"mythicalCapeTier":{"value":0},"graveDiggerProperties":{"points":{"value":0},"attempts":{"value":3},"paidAttempts":{"value":0}},"openedGift":false,"unlcaimedPrizes":[]},"miglo":{"id":"miglo","slayerPoints":{"value":3},"preferCap":{"value":1},"blockCap":{"value":1},"tasksCompleted":{"value":2},"taskStreak":{"value":2},"preferredTasks":[],"blockedTasks":[],"unlocksList":[],"slayerTask":{"assignment":35,"amount":{"value":52},"master":403},"slayerMaster":403,"herbSack":{},"paymentRunes":[],"magicFindRating":{"value":0},"mythicalCapeCharges":{"value":0},"mythicalCapeTier":{"value":0},"graveDiggerProperties":{"points":{"value":0},"attempts":{"value":3},"paidAttempts":{"value":0}},"openedGift":false,"unlcaimedPrizes":[]},"moot":{"id":"moot","slayerPoints":{"value":0},"preferCap":{"value":1},"blockCap":{"value":1},"tasksCompleted":{"value":0},"taskStreak":{"value":0},"preferredTasks":[],"blockedTasks":[],"unlocksList":[],"slayerTask":{"assignment":16,"amount":{"value":17},"master":402},"slayerMaster":402,"herbSack":{},"paymentRunes":[],"magicFindRating":{"value":0},"mythicalCapeCharges":{"value":0},"mythicalCapeTier":{"value":0},"graveDiggerProperties":{"points":{"value":0},"attempts":{"value":3},"paidAttempts":{"value":0}},"openedGift":false,"unlcaimedPrizes":[]},"fanta":{"id":"fanta","slayerPoints":{"value":0},"preferCap":{"value":1},"blockCap":{"value":1},"tasksCompleted":{"value":0},"taskStreak":{"value":0},"preferredTasks":[],"blockedTasks":[],"unlocksList":[],"slayerTask":{"assignment":25,"amount":{"value":131},"master":404},"slayerMaster":404,"herbSack":{},"paymentRunes":[],"magicFindRating":{"value":0},"mythicalCapeCharges":{"value":0},"mythicalCapeTier":{"value":0},"graveDiggerProperties":{"points":{"value":0},"attempts":{"value":3},"paidAttempts":{"value":0}},"openedGift":false,"unlcaimedPrizes":[]},"christian":{"id":"christian","slayerPoints":{"value":105},"preferCap":{"value":1},"blockCap":{"value":1},"tasksCompleted":{"value":30},"taskStreak":{"value":30},"preferredTasks":[],"blockedTasks":[],"unlocksList":[],"slayerTask":{"assignment":21,"amount":{"value":42},"master":401},"slayerMaster":401,"herbSack":{},"paymentRunes":[],"magicFindRating":{"value":400},"mythicalCapeCharges":{"value":0},"mythicalCapeTier":{"value":0},"graveDiggerProperties":{"points":{"value":0},"attempts":{"value":3},"paidAttempts":{"value":0}},"openedGift":false,"unlcaimedPrizes":[]},"mozzie":{"id":"mozzie","slayerPoints":{"value":0},"preferCap":{"value":1},"blockCap":{"value":1},"tasksCompleted":{"value":0},"taskStreak":{"value":0},"preferredTasks":[],"blockedTasks":[],"unlocksList":[],"slayerTask":{"assignment":21,"amount":{"value":15},"master":401},"slayerMaster":401,"herbSack":{},"paymentRunes":[],"magicFindRating":{"value":0},"mythicalCapeCharges":{"value":0},"mythicalCapeTier":{"value":0},"graveDiggerProperties":{"points":{"value":0},"attempts":{"value":3},"paidAttempts":{"value":0}},"openedGift":false,"unlcaimedPrizes":[]},"peep show":{"id":"peep show","slayerPoints":{"value":3},"preferCap":{"value":1},"blockCap":{"value":1},"tasksCompleted":{"value":2},"taskStreak":{"value":2},"preferredTasks":[],"blockedTasks":[],"unlocksList":[],"slayerTask":{"assignment":26,"amount":{"value":110},"master":403},"slayerMaster":403,"herbSack":{},"paymentRunes":[],"magicFindRating":{"value":0},"mythicalCapeCharges":{"value":0},"mythicalCapeTier":{"value":0},"graveDiggerProperties":{"points":{"value":0},"attempts":{"value":3},"paidAttempts":{"value":0}},"openedGift":false,"unlcaimedPrizes":[]},"links":{"id":"links","slayerPoints":{"value":1},"preferCap":{"value":1},"blockCap":{"value":1},"tasksCompleted":{"value":1},"taskStreak":{"value":1},"preferredTasks":[],"blockedTasks":[],"unlocksList":[],"slayerMaster":401,"herbSack":{},"paymentRunes":[],"magicFindRating":{"value":0},"mythicalCapeCharges":{"value":0},"mythicalCapeTier":{"value":0},"graveDiggerProperties":{"points":{"value":0},"attempts":{"value":3},"paidAttempts":{"value":0}},"openedGift":false,"unlcaimedPrizes":[]},"allie boo":{"id":"allie boo","slayerPoints":{"value":0},"preferCap":{"value":1},"blockCap":{"value":1},"tasksCompleted":{"value":0},"taskStreak":{"value":0},"preferredTasks":[],"blockedTasks":[],"unlocksList":[],"slayerMaster":0,"herbSack":{},"paymentRunes":[],"magicFindRating":{"value":0},"mythicalCapeCharges":{"value":0},"mythicalCapeTier":{"value":0},"graveDiggerProperties":{"points":{"value":0},"attempts":{"value":3},"paidAttempts":{"value":0}},"openedGift":false,"unlcaimedPrizes":[]}}}